Metadata-Version: 2.1
Name: processamento_de_img
Version: 0.1
Summary:  pacote simples para Processamento de imagem em Python
Home-page: https://github.com/GubioGL/BootCampDIO
Author: Nick: Oibug/Nome:Gubio Gomes De Lima
Author-email: gubiojogo@gmail.com
Requires-Python: >=3.10
Requires-Dist: numpy
Requires-Dist: matplotlib
Requires-Dist: scikit-image
